{"nodes": [{"node": 0, "name": "msn.com", "colour": "#f8765c"}, {"node": 1, "name": "adyoulike.com", "colour": "#eb5760"}, {"node": 2, "name": "affinity.com", "colour": "#eb5760"}, {"node": 3, "name": "andbeyond.media", "colour": "#eb5760"}, {"node": 4, "name": "arkadium.com", "colour": "#eb5760"}, {"node": 5, "name": "digiteka.com", "colour": "#eb5760"}, {"node": 6, "name": "egami.tv", "colour": "#eb5760"}, {"node": 7, "name": "inskinmedia.com", "colour": "#eb5760"}, {"node": 8, "name": "liveintent.com", "colour": "#eb5760"}, {"node": 9, "name": "media.net", "colour": "#eb5760"}, {"node": 10, "name": "mgid.com", "colour": "#eb5760"}, {"node": 11, "name": "onetag.com", "colour": "#eb5760"}, {"node": 12, "name": "reklamstore.com", "colour": "#eb5760"}, {"node": 13, "name": "rtbdemand.com", "colour": "#eb5760"}, {"node": 14, "name": "seedtag.com", "colour": "#eb5760"}, {"node": 15, "name": "specto.tv", "colour": "#eb5760"}, {"node": 16, "name": "taboola.com", "colour": "#eb5760"}, {"node": 17, "name": "teads.tv", "colour": "#eb5760"}, {"node": 18, "name": "truvid.com", "colour": "#eb5760"}, {"node": 19, "name": "vdo.ai", "colour": "#eb5760"}, {"node": 20, "name": "velismedia.com", "colour": "#eb5760"}, {"node": 21, "name": "verizonmedia.com", "colour": "#eb5760"}, {"node": 22, "name": "vidmatic.tv", "colour": "#eb5760"}, {"node": 23, "name": "appnexus.com", "colour": "#d3436e"}, {"node": 24, "name": "freewheel.com", "colour": "#d3436e"}, {"node": 25, "name": "freewheel.tv", "colour": "#d3436e"}, {"node": 26, "name": "impactify.io", "colour": "#d3436e"}, {"node": 27, "name": "mobfox.com", "colour": "#d3436e"}, {"node": 28, "name": "openx.com", "colour": "#d3436e"}, {"node": 29, "name": "rubiconproject.com", "colour": "#d3436e"}, {"node": 30, "name": "showheroes.com", "colour": "#d3436e"}, {"node": 31, "name": "spotx.tv", "colour": "#d3436e"}, {"node": 32, "name": "xandr.com", "colour": "#d3436e"}, {"node": 33, "name": "insticator.com", "colour": "#d3436e"}, {"node": 34, "name": "lijit.com", "colour": "#d3436e"}, {"node": 35, "name": "pubmatic.com", "colour": "#d3436e"}, {"node": 36, "name": "adagio.io", "colour": "#d3436e"}, {"node": 37, "name": "districtm.io", "colour": "#d3436e"}, {"node": 38, "name": "districtm.net", "colour": "#d3436e"}, {"node": 39, "name": "smartadserver.com", "colour": "#d3436e"}, {"node": 40, "name": "smartadserver.fr", "colour": "#d3436e"}, {"node": 41, "name": "33across.com", "colour": "#d3436e"}, {"node": 42, "name": "adcolony.com", "colour": "#d3436e"}, {"node": 43, "name": "admanmedia.com", "colour": "#d3436e"}, {"node": 44, "name": "conversantmedia.com", "colour": "#d3436e"}, {"node": 45, "name": "gumgum.com", "colour": "#d3436e"}, {"node": 46, "name": "indexexchange.com", "colour": "#d3436e"}, {"node": 47, "name": "insightimage.com", "colour": "#d3436e"}, {"node": 48, "name": "pulsepoint.com", "colour": "#d3436e"}, {"node": 49, "name": "rhythmone.com", "colour": "#d3436e"}, {"node": 50, "name": "sonobi.com", "colour": "#d3436e"}, {"node": 51, "name": "triplelift.com", "colour": "#d3436e"}, {"node": 52, "name": "yieldmo.com", "colour": "#d3436e"}, {"node": 53, "name": "improvedigital.com", "colour": "#d3436e"}, {"node": 54, "name": "smartclip.net", "colour": "#d3436e"}, {"node": 55, "name": "beachfront.com", "colour": "#d3436e"}, {"node": 56, "name": "beachfrontmedia.com", "colour": "#d3436e"}, {"node": 57, "name": "gay.it", "colour": "#d3436e"}, {"node": 58, "name": "lunamedia.io", "colour": "#d3436e"}, {"node": 59, "name": "sortable.com", "colour": "#d3436e"}, {"node": 60, "name": "springserve.com", "colour": "#d3436e"}, {"node": 61, "name": "brealtime.com", "colour": "#d3436e"}, {"node": 62, "name": "emxdigital.com", "colour": "#d3436e"}, {"node": 63, "name": "playbuzz.com", "colour": "#d3436e"}, {"node": 64, "name": "sharethrough.com", "colour": "#d3436e"}, {"node": 65, "name": "admixer.com", "colour": "#d3436e"}, {"node": 66, "name": "admixer.net", "colour": "#d3436e"}, {"node": 67, "name": "advenuemedia.co.uk", "colour": "#d3436e"}, {"node": 68, "name": "aniview.com", "colour": "#d3436e"}, {"node": 69, "name": "apacdex.com", "colour": "#d3436e"}, {"node": 70, "name": "cedato.com", "colour": "#d3436e"}, {"node": 71, "name": "connatix.com", "colour": "#d3436e"}, {"node": 72, "name": "fout.jp", "colour": "#d3436e"}, {"node": 73, "name": "freegames66.com", "colour": "#d3436e"}, {"node": 74, "name": "h12ukltd.com", "colour": "#d3436e"}, {"node": 75, "name": "interdogmedia.com", "colour": "#d3436e"}, {"node": 76, "name": "kubient.com", "colour": "#d3436e"}, {"node": 77, "name": "loopme.com", "colour": "#d3436e"}, {"node": 78, "name": "newborntown.com", "colour": "#d3436e"}, {"node": 79, "name": "quantumdex.io", "colour": "#d3436e"}, {"node": 80, "name": "valueimpression.com", "colour": "#d3436e"}, {"node": 81, "name": "viralize.com", "colour": "#d3436e"}, {"node": 82, "name": "vyadd.com", "colour": "#d3436e"}, {"node": 83, "name": "germaniavid.com", "colour": "#d3436e"}, {"node": 84, "name": "phonder.com", "colour": "#d3436e"}, {"node": 85, "name": "152media.info", "colour": "#d3436e"}, {"node": 86, "name": "revlift.io", "colour": "#d3436e"}, {"node": 87, "name": "vidazoo.com", "colour": "#d3436e"}, {"node": 88, "name": "publicidad.net", "colour": "#d3436e"}, {"node": 89, "name": "richaudience.com", "colour": "#d3436e"}, {"node": 90, "name": "aerserv.com", "colour": "#d3436e"}, {"node": 91, "name": "aol.com", "colour": "#d3436e"}, {"node": 92, "name": "bidmachine.io", "colour": "#d3436e"}, {"node": 93, "name": "inmobi.com", "colour": "#d3436e"}, {"node": 94, "name": "lkqd.com", "colour": "#d3436e"}, {"node": 95, "name": "synacor.com", "colour": "#d3436e"}, {"node": 96, "name": "yahoo.com", "colour": "#d3436e"}, {"node": 97, "name": "ad-generation.jp", "colour": "#d3436e"}, {"node": 98, "name": "e-planning.net", "colour": "#d3436e"}, {"node": 99, "name": "lemmatechnologies.com", "colour": "#d3436e"}, {"node": 100, "name": "sabiomobile.com", "colour": "#d3436e"}, {"node": 101, "name": "vrtcal.com", "colour": "#d3436e"}, {"node": 102, "name": "axonix.com", "colour": "#d3436e"}, {"node": 103, "name": "blis.com", "colour": "#d3436e"}, {"node": 104, "name": "impact-ad.jp", "colour": "#d3436e"}, {"node": 105, "name": "piximedia.com", "colour": "#d3436e"}, {"node": 106, "name": "pokkt.com", "colour": "#d3436e"}, {"node": 107, "name": "spot.im", "colour": "#d3436e"}, {"node": 108, "name": "spotim.market", "colour": "#d3436e"}, {"node": 109, "name": "digitize.ie", "colour": "#b5367a"}, {"node": 110, "name": "waardex.com", "colour": "#b5367a"}, {"node": 111, "name": "omnijay.com", "colour": "#b5367a"}, {"node": 112, "name": "playwire.com", "colour": "#b5367a"}, {"node": 113, "name": "playwiremedia.com", "colour": "#b5367a"}, {"node": 114, "name": "adsolut.in", "colour": "#b5367a"}, {"node": 115, "name": "amlinetwork.com", "colour": "#b5367a"}, {"node": 116, "name": "gothamads.com", "colour": "#b5367a"}, {"node": 117, "name": "groundtruth.com", "colour": "#b5367a"}, {"node": 118, "name": "mars.media", "colour": "#b5367a"}, {"node": 119, "name": "mars.video", "colour": "#b5367a"}, {"node": 120, "name": "resultsmedia.com", "colour": "#b5367a"}, {"node": 121, "name": "vidstart.com", "colour": "#b5367a"}, {"node": 122, "name": "madvertise.com", "colour": "#b5367a"}, {"node": 123, "name": "madvertise.it", "colour": "#b5367a"}, {"node": 124, "name": "ogury.co", "colour": "#b5367a"}, {"node": 125, "name": "ogury.com", "colour": "#b5367a"}, {"node": 126, "name": "playground.xyz", "colour": "#b5367a"}, {"node": 127, "name": "justpremium.com", "colour": "#b5367a"}, {"node": 128, "name": "smartstream.tv", "colour": "#b5367a"}, {"node": 129, "name": "union.media", "colour": "#b5367a"}, {"node": 130, "name": "yieldlab.net", "colour": "#b5367a"}, {"node": 131, "name": "audienciad.com", "colour": "#b5367a"}, {"node": 132, "name": "brightcom.com", "colour": "#b5367a"}, {"node": 133, "name": "limpid.tv", "colour": "#b5367a"}, {"node": 134, "name": "yieldnexus.com", "colour": "#b5367a"}, {"node": 135, "name": "nativo.com", "colour": "#b5367a"}, {"node": 136, "name": "nativo.net", "colour": "#b5367a"}, {"node": 137, "name": "fueldigitalmedia.com", "colour": "#b5367a"}, {"node": 138, "name": "hcodemedia.com", "colour": "#b5367a"}, {"node": 139, "name": "smaato.com", "colour": "#b5367a"}, {"node": 140, "name": "gammassp.com", "colour": "#b5367a"}, {"node": 141, "name": "verve.com", "colour": "#b5367a"}, {"node": 142, "name": "colossusssp.com", "colour": "#b5367a"}, {"node": 143, "name": "relappro.com", "colour": "#b5367a"}, {"node": 144, "name": "trion.io", "colour": "#b5367a"}, {"node": 145, "name": "trioninteractive.com", "colour": "#b5367a"}, {"node": 146, "name": "anyclip.com", "colour": "#b5367a"}, {"node": 147, "name": "saambaa.com", "colour": "#b5367a"}, {"node": 148, "name": "vidcrunch.com", "colour": "#b5367a"}, {"node": 149, "name": "fyber.com", "colour": "#b5367a"}, {"node": 150, "name": "optimanetwork.com", "colour": "#b5367a"}, {"node": 151, "name": "leonardoadv.it", "colour": "#b5367a"}, {"node": 152, "name": "mediaprime.it", "colour": "#b5367a"}, {"node": 153, "name": "primerealtime.com", "colour": "#b5367a"}, {"node": 154, "name": "triboo.com", "colour": "#b5367a"}, {"node": 155, "name": "triboo.it", "colour": "#b5367a"}, {"node": 156, "name": "krushmedia.com", "colour": "#b5367a"}, {"node": 157, "name": "pmc.com", "colour": "#b5367a"}, {"node": 158, "name": "shemedia.com", "colour": "#b5367a"}, {"node": 159, "name": "altitude-arena.com", "colour": "#b5367a"}, {"node": 160, "name": "undertone.com", "colour": "#b5367a"}, {"node": 161, "name": "adapex.io", "colour": "#b5367a"}, {"node": 162, "name": "amazon.com", "colour": "#b5367a"}, {"node": 163, "name": "pixfuture.com", "colour": "#b5367a"}, {"node": 164, "name": "mobcomedia.com", "colour": "#b5367a"}, {"node": 165, "name": "redzone.digital", "colour": "#b5367a"}, {"node": 166, "name": "avantisvideo.com", "colour": "#b5367a"}, {"node": 167, "name": "nobid.io", "colour": "#b5367a"}, {"node": 168, "name": "betweendigital.com", "colour": "#b5367a"}, {"node": 169, "name": "adview.com", "colour": "#b5367a"}, {"node": 170, "name": "ironsrc.com", "colour": "#b5367a"}, {"node": 171, "name": "tapjoy.com", "colour": "#b5367a"}, {"node": 172, "name": "adform.com", "colour": "#b5367a"}, {"node": 173, "name": "movingup.it", "colour": "#b5367a"}, {"node": 174, "name": "next14.com", "colour": "#b5367a"}, {"node": 175, "name": "pearlyadx.com", "colour": "#b5367a"}, {"node": 176, "name": "startapp.com", "colour": "#b5367a"}, {"node": 177, "name": "venatusmedia.com", "colour": "#b5367a"}, {"node": 178, "name": "consumable.com", "colour": "#b5367a"}, {"node": 179, "name": "distroscale.com", "colour": "#b5367a"}, {"node": 180, "name": "giftconnect.com", "colour": "#b5367a"}, {"node": 181, "name": "plista.com", "colour": "#b5367a"}, {"node": 182, "name": "adsmovil.com", "colour": "#b5367a"}, {"node": 183, "name": "nglcollective.com", "colour": "#b5367a"}, {"node": 184, "name": "nglmedia.com", "colour": "#b5367a"}, {"node": 185, "name": "leanback.digital", "colour": "#b5367a"}, {"node": 186, "name": "momagic.com", "colour": "#b5367a"}, {"node": 187, "name": "bat-ads.com", "colour": "#982d80"}, {"node": 188, "name": "aax.media", "colour": "#982d80"}, {"node": 189, "name": "infolinks.com", "colour": "#982d80"}, {"node": 190, "name": "reforge.in", "colour": "#982d80"}, {"node": 191, "name": "luponmedia.com", "colour": "#982d80"}, {"node": 192, "name": "yoc.com", "colour": "#982d80"}, {"node": 193, "name": "chartboost.com", "colour": "#982d80"}, {"node": 194, "name": "clusteradmedia.com", "colour": "#982d80"}, {"node": 195, "name": "samba.tv", "colour": "#982d80"}, {"node": 196, "name": "rtk.io", "colour": "#982d80"}, {"node": 197, "name": "udmserve.net", "colour": "#982d80"}, {"node": 198, "name": "underdogmedia.com", "colour": "#982d80"}, {"node": 199, "name": "projectagora.com", "colour": "#982d80"}, {"node": 200, "name": "brid.tv", "colour": "#982d80"}, {"node": 201, "name": "tritondigital.com", "colour": "#982d80"}, {"node": 202, "name": "zedo.com", "colour": "#982d80"}, {"node": 203, "name": "adpone.com", "colour": "#982d80"}, {"node": 204, "name": "apester.com", "colour": "#982d80"}, {"node": 205, "name": "primis.tech", "colour": "#982d80"}, {"node": 206, "name": "tappx.com", "colour": "#982d80"}, {"node": 207, "name": "adbility-media.com", "colour": "#982d80"}, {"node": 208, "name": "adscale.de", "colour": "#982d80"}, {"node": 209, "name": "hoopladigital.co.uk", "colour": "#982d80"}, {"node": 210, "name": "stroeer.com", "colour": "#982d80"}, {"node": 211, "name": "stroeer.de", "colour": "#982d80"}, {"node": 212, "name": "lifestreet.com", "colour": "#982d80"}, {"node": 213, "name": "somoaudience.com", "colour": "#982d80"}, {"node": 214, "name": "selectmedia.asia", "colour": "#7b2382"}, {"node": 215, "name": "sunmedia.tv", "colour": "#7b2382"}, {"node": 216, "name": "sovrnservices.com", "colour": "#7b2382"}, {"node": 217, "name": "webfg.com", "colour": "#5f187f"}, {"node": 218, "name": "webfinancialgroup.com", "colour": "#5f187f"}], "links": [{"source": 0, "target": 1, "value": 1, "colour": "#f8765c"}, {"source": 0, "target": 2, "value": 1, "colour": "#f8765c"}, {"source": 0, "target": 3, "value": 1, "colour": "#f8765c"}, {"source": 0, "target": 4, "value": 1, "colour": "#f8765c"}, {"source": 0, "target": 5, "value": 1, "colour": "#f8765c"}, {"source": 0, "target": 6, "value": 1, "colour": "#f8765c"}, {"source": 0, "target": 7, "value": 1, "colour": "#f8765c"}, {"source": 0, "target": 8, "value": 1, "colour": "#f8765c"}, {"source": 0, "target": 9, "value": 1, "colour": "#f8765c"}, {"source": 0, "target": 10, "value": 1, "colour": "#f8765c"}, {"source": 0, "target": 11, "value": 1, "colour": "#f8765c"}, {"source": 0, "target": 12, "value": 1, "colour": "#f8765c"}, {"source": 0, "target": 13, "value": 1, "colour": "#f8765c"}, {"source": 0, "target": 14, "value": 1, "colour": "#f8765c"}, {"source": 0, "target": 15, "value": 1, "colour": "#f8765c"}, {"source": 0, "target": 16, "value": 1, "colour": "#f8765c"}, {"source": 0, "target": 17, "value": 1, "colour": "#f8765c"}, {"source": 0, "target": 18, "value": 1, "colour": "#f8765c"}, {"source": 0, "target": 19, "value": 1, "colour": "#f8765c"}, {"source": 0, "target": 20, "value": 1, "colour": "#f8765c"}, {"source": 0, "target": 21, "value": 1, "colour": "#f8765c"}, {"source": 0, "target": 22, "value": 1, "colour": "#f8765c"}, {"source": 1, "target": 23, "value": 1, "colour": "#eb5760"}, {"source": 1, "target": 24, "value": 1, "colour": "#eb5760"}, {"source": 1, "target": 25, "value": 1, "colour": "#eb5760"}, {"source": 1, "target": 26, "value": 1, "colour": "#eb5760"}, {"source": 1, "target": 27, "value": 1, "colour": "#eb5760"}, {"source": 1, "target": 28, "value": 1, "colour": "#eb5760"}, {"source": 1, "target": 29, "value": 1, "colour": "#eb5760"}, {"source": 1, "target": 30, "value": 1, "colour": "#eb5760"}, {"source": 1, "target": 31, "value": 1, "colour": "#eb5760"}, {"source": 1, "target": 32, "value": 1, "colour": "#eb5760"}, {"source": 2, "target": 23, "value": 1, "colour": "#eb5760"}, {"source": 2, "target": 33, "value": 1, "colour": "#eb5760"}, {"source": 2, "target": 34, "value": 1, "colour": "#eb5760"}, {"source": 2, "target": 35, "value": 1, "colour": "#eb5760"}, {"source": 2, "target": 32, "value": 1, "colour": "#eb5760"}, {"source": 3, "target": 36, "value": 1, "colour": "#eb5760"}, {"source": 3, "target": 37, "value": 1, "colour": "#eb5760"}, {"source": 3, "target": 38, "value": 1, "colour": "#eb5760"}, {"source": 3, "target": 34, "value": 1, "colour": "#eb5760"}, {"source": 3, "target": 35, "value": 1, "colour": "#eb5760"}, {"source": 3, "target": 29, "value": 1, "colour": "#eb5760"}, {"source": 3, "target": 39, "value": 1, "colour": "#eb5760"}, {"source": 3, "target": 40, "value": 1, "colour": "#eb5760"}, {"source": 4, "target": 41, "value": 1, "colour": "#eb5760"}, {"source": 4, "target": 42, "value": 1, "colour": "#eb5760"}, {"source": 4, "target": 43, "value": 1, "colour": "#eb5760"}, {"source": 4, "target": 23, "value": 1, "colour": "#eb5760"}, {"source": 4, "target": 44, "value": 1, "colour": "#eb5760"}, {"source": 4, "target": 37, "value": 1, "colour": "#eb5760"}, {"source": 4, "target": 38, "value": 1, "colour": "#eb5760"}, {"source": 4, "target": 45, "value": 1, "colour": "#eb5760"}, {"source": 4, "target": 46, "value": 1, "colour": "#eb5760"}, {"source": 4, "target": 47, "value": 1, "colour": "#eb5760"}, {"source": 4, "target": 34, "value": 1, "colour": "#eb5760"}, {"source": 4, "target": 28, "value": 1, "colour": "#eb5760"}, {"source": 4, "target": 35, "value": 1, "colour": "#eb5760"}, {"source": 4, "target": 48, "value": 1, "colour": "#eb5760"}, {"source": 4, "target": 49, "value": 1, "colour": "#eb5760"}, {"source": 4, "target": 29, "value": 1, "colour": "#eb5760"}, {"source": 4, "target": 39, "value": 1, "colour": "#eb5760"}, {"source": 4, "target": 40, "value": 1, "colour": "#eb5760"}, {"source": 4, "target": 50, "value": 1, "colour": "#eb5760"}, {"source": 4, "target": 31, "value": 1, "colour": "#eb5760"}, {"source": 4, "target": 51, "value": 1, "colour": "#eb5760"}, {"source": 4, "target": 32, "value": 1, "colour": "#eb5760"}, {"source": 4, "target": 52, "value": 1, "colour": "#eb5760"}, {"source": 5, "target": 43, "value": 1, "colour": "#eb5760"}, {"source": 5, "target": 23, "value": 1, "colour": "#eb5760"}, {"source": 5, "target": 24, "value": 1, "colour": "#eb5760"}, {"source": 5, "target": 25, "value": 1, "colour": "#eb5760"}, {"source": 5, "target": 53, "value": 1, "colour": "#eb5760"}, {"source": 5, "target": 46, "value": 1, "colour": "#eb5760"}, {"source": 5, "target": 29, "value": 1, "colour": "#eb5760"}, {"source": 5, "target": 39, "value": 1, "colour": "#eb5760"}, {"source": 5, "target": 40, "value": 1, "colour": "#eb5760"}, {"source": 5, "target": 54, "value": 1, "colour": "#eb5760"}, {"source": 5, "target": 31, "value": 1, "colour": "#eb5760"}, {"source": 5, "target": 32, "value": 1, "colour": "#eb5760"}, {"source": 6, "target": 41, "value": 1, "colour": "#eb5760"}, {"source": 6, "target": 55, "value": 1, "colour": "#eb5760"}, {"source": 6, "target": 56, "value": 1, "colour": "#eb5760"}, {"source": 6, "target": 57, "value": 1, "colour": "#eb5760"}, {"source": 6, "target": 58, "value": 1, "colour": "#eb5760"}, {"source": 6, "target": 28, "value": 1, "colour": "#eb5760"}, {"source": 6, "target": 35, "value": 1, "colour": "#eb5760"}, {"source": 6, "target": 49, "value": 1, "colour": "#eb5760"}, {"source": 6, "target": 39, "value": 1, "colour": "#eb5760"}, {"source": 6, "target": 40, "value": 1, "colour": "#eb5760"}, {"source": 6, "target": 59, "value": 1, "colour": "#eb5760"}, {"source": 6, "target": 60, "value": 1, "colour": "#eb5760"}, {"source": 7, "target": 46, "value": 1, "colour": "#eb5760"}, {"source": 8, "target": 23, "value": 1, "colour": "#eb5760"}, {"source": 8, "target": 48, "value": 1, "colour": "#eb5760"}, {"source": 8, "target": 32, "value": 1, "colour": "#eb5760"}, {"source": 9, "target": 41, "value": 1, "colour": "#eb5760"}, {"source": 9, "target": 23, "value": 1, "colour": "#eb5760"}, {"source": 9, "target": 61, "value": 1, "colour": "#eb5760"}, {"source": 9, "target": 44, "value": 1, "colour": "#eb5760"}, {"source": 9, "target": 37, "value": 1, "colour": "#eb5760"}, {"source": 9, "target": 38, "value": 1, "colour": "#eb5760"}, {"source": 9, "target": 62, "value": 1, "colour": "#eb5760"}, {"source": 9, "target": 34, "value": 1, "colour": "#eb5760"}, {"source": 9, "target": 28, "value": 1, "colour": "#eb5760"}, {"source": 9, "target": 63, "value": 1, "colour": "#eb5760"}, {"source": 9, "target": 35, "value": 1, "colour": "#eb5760"}, {"source": 9, "target": 49, "value": 1, "colour": "#eb5760"}, {"source": 9, "target": 29, "value": 1, "colour": "#eb5760"}, {"source": 9, "target": 64, "value": 1, "colour": "#eb5760"}, {"source": 9, "target": 50, "value": 1, "colour": "#eb5760"}, {"source": 9, "target": 31, "value": 1, "colour": "#eb5760"}, {"source": 9, "target": 32, "value": 1, "colour": "#eb5760"}, {"source": 10, "target": 65, "value": 1, "colour": "#eb5760"}, {"source": 10, "target": 66, "value": 1, "colour": "#eb5760"}, {"source": 10, "target": 67, "value": 1, "colour": "#eb5760"}, {"source": 10, "target": 68, "value": 1, "colour": "#eb5760"}, {"source": 10, "target": 69, "value": 1, "colour": "#eb5760"}, {"source": 10, "target": 70, "value": 1, "colour": "#eb5760"}, {"source": 10, "target": 71, "value": 1, "colour": "#eb5760"}, {"source": 10, "target": 72, "value": 1, "colour": "#eb5760"}, {"source": 10, "target": 73, "value": 1, "colour": "#eb5760"}, {"source": 10, "target": 57, "value": 1, "colour": "#eb5760"}, {"source": 10, "target": 74, "value": 1, "colour": "#eb5760"}, {"source": 10, "target": 75, "value": 1, "colour": "#eb5760"}, {"source": 10, "target": 76, "value": 1, "colour": "#eb5760"}, {"source": 10, "target": 77, "value": 1, "colour": "#eb5760"}, {"source": 10, "target": 78, "value": 1, "colour": "#eb5760"}, {"source": 10, "target": 79, "value": 1, "colour": "#eb5760"}, {"source": 10, "target": 29, "value": 1, "colour": "#eb5760"}, {"source": 10, "target": 39, "value": 1, "colour": "#eb5760"}, {"source": 10, "target": 40, "value": 1, "colour": "#eb5760"}, {"source": 10, "target": 31, "value": 1, "colour": "#eb5760"}, {"source": 10, "target": 80, "value": 1, "colour": "#eb5760"}, {"source": 10, "target": 81, "value": 1, "colour": "#eb5760"}, {"source": 10, "target": 82, "value": 1, "colour": "#eb5760"}, {"source": 11, "target": 83, "value": 1, "colour": "#eb5760"}, {"source": 12, "target": 23, "value": 1, "colour": "#eb5760"}, {"source": 12, "target": 24, "value": 1, "colour": "#eb5760"}, {"source": 12, "target": 25, "value": 1, "colour": "#eb5760"}, {"source": 12, "target": 53, "value": 1, "colour": "#eb5760"}, {"source": 12, "target": 27, "value": 1, "colour": "#eb5760"}, {"source": 12, "target": 84, "value": 1, "colour": "#eb5760"}, {"source": 12, "target": 35, "value": 1, "colour": "#eb5760"}, {"source": 12, "target": 29, "value": 1, "colour": "#eb5760"}, {"source": 12, "target": 32, "value": 1, "colour": "#eb5760"}, {"source": 13, "target": 85, "value": 1, "colour": "#eb5760"}, {"source": 13, "target": 68, "value": 1, "colour": "#eb5760"}, {"source": 13, "target": 71, "value": 1, "colour": "#eb5760"}, {"source": 13, "target": 37, "value": 1, "colour": "#eb5760"}, {"source": 13, "target": 38, "value": 1, "colour": "#eb5760"}, {"source": 13, "target": 24, "value": 1, "colour": "#eb5760"}, {"source": 13, "target": 25, "value": 1, "colour": "#eb5760"}, {"source": 13, "target": 46, "value": 1, "colour": "#eb5760"}, {"source": 13, "target": 28, "value": 1, "colour": "#eb5760"}, {"source": 13, "target": 86, "value": 1, "colour": "#eb5760"}, {"source": 13, "target": 31, "value": 1, "colour": "#eb5760"}, {"source": 13, "target": 51, "value": 1, "colour": "#eb5760"}, {"source": 13, "target": 87, "value": 1, "colour": "#eb5760"}, {"source": 14, "target": 41, "value": 1, "colour": "#eb5760"}, {"source": 14, "target": 23, "value": 1, "colour": "#eb5760"}, {"source": 14, "target": 57, "value": 1, "colour": "#eb5760"}, {"source": 14, "target": 53, "value": 1, "colour": "#eb5760"}, {"source": 14, "target": 88, "value": 1, "colour": "#eb5760"}, {"source": 14, "target": 35, "value": 1, "colour": "#eb5760"}, {"source": 14, "target": 89, "value": 1, "colour": "#eb5760"}, {"source": 14, "target": 29, "value": 1, "colour": "#eb5760"}, {"source": 14, "target": 39, "value": 1, "colour": "#eb5760"}, {"source": 14, "target": 40, "value": 1, "colour": "#eb5760"}, {"source": 14, "target": 31, "value": 1, "colour": "#eb5760"}, {"source": 14, "target": 32, "value": 1, "colour": "#eb5760"}, {"source": 15, "target": 53, "value": 1, "colour": "#eb5760"}, {"source": 16, "target": 43, "value": 1, "colour": "#eb5760"}, {"source": 16, "target": 65, "value": 1, "colour": "#eb5760"}, {"source": 16, "target": 66, "value": 1, "colour": "#eb5760"}, {"source": 16, "target": 90, "value": 1, "colour": "#eb5760"}, {"source": 16, "target": 91, "value": 1, "colour": "#eb5760"}, {"source": 16, "target": 23, "value": 1, "colour": "#eb5760"}, {"source": 16, "target": 55, "value": 1, "colour": "#eb5760"}, {"source": 16, "target": 56, "value": 1, "colour": "#eb5760"}, {"source": 16, "target": 92, "value": 1, "colour": "#eb5760"}, {"source": 16, "target": 61, "value": 1, "colour": "#eb5760"}, {"source": 16, "target": 62, "value": 1, "colour": "#eb5760"}, {"source": 16, "target": 24, "value": 1, "colour": "#eb5760"}, {"source": 16, "target": 25, "value": 1, "colour": "#eb5760"}, {"source": 16, "target": 46, "value": 1, "colour": "#eb5760"}, {"source": 16, "target": 93, "value": 1, "colour": "#eb5760"}, {"source": 16, "target": 94, "value": 1, "colour": "#eb5760"}, {"source": 16, "target": 77, "value": 1, "colour": "#eb5760"}, {"source": 16, "target": 28, "value": 1, "colour": "#eb5760"}, {"source": 16, "target": 35, "value": 1, "colour": "#eb5760"}, {"source": 16, "target": 48, "value": 1, "colour": "#eb5760"}, {"source": 16, "target": 49, "value": 1, "colour": "#eb5760"}, {"source": 16, "target": 29, "value": 1, "colour": "#eb5760"}, {"source": 16, "target": 39, "value": 1, "colour": "#eb5760"}, {"source": 16, "target": 40, "value": 1, "colour": "#eb5760"}, {"source": 16, "target": 31, "value": 1, "colour": "#eb5760"}, {"source": 16, "target": 60, "value": 1, "colour": "#eb5760"}, {"source": 16, "target": 95, "value": 1, "colour": "#eb5760"}, {"source": 16, "target": 32, "value": 1, "colour": "#eb5760"}, {"source": 16, "target": 96, "value": 1, "colour": "#eb5760"}, {"source": 17, "target": 97, "value": 1, "colour": "#eb5760"}, {"source": 17, "target": 23, "value": 1, "colour": "#eb5760"}, {"source": 17, "target": 48, "value": 1, "colour": "#eb5760"}, {"source": 17, "target": 32, "value": 1, "colour": "#eb5760"}, {"source": 18, "target": 68, "value": 1, "colour": "#eb5760"}, {"source": 18, "target": 24, "value": 1, "colour": "#eb5760"}, {"source": 18, "target": 25, "value": 1, "colour": "#eb5760"}, {"source": 18, "target": 57, "value": 1, "colour": "#eb5760"}, {"source": 18, "target": 35, "value": 1, "colour": "#eb5760"}, {"source": 18, "target": 49, "value": 1, "colour": "#eb5760"}, {"source": 18, "target": 29, "value": 1, "colour": "#eb5760"}, {"source": 18, "target": 39, "value": 1, "colour": "#eb5760"}, {"source": 18, "target": 40, "value": 1, "colour": "#eb5760"}, {"source": 18, "target": 54, "value": 1, "colour": "#eb5760"}, {"source": 19, "target": 41, "value": 1, "colour": "#eb5760"}, {"source": 19, "target": 68, "value": 1, "colour": "#eb5760"}, {"source": 19, "target": 23, "value": 1, "colour": "#eb5760"}, {"source": 19, "target": 37, "value": 1, "colour": "#eb5760"}, {"source": 19, "target": 38, "value": 1, "colour": "#eb5760"}, {"source": 19, "target": 98, "value": 1, "colour": "#eb5760"}, {"source": 19, "target": 24, "value": 1, "colour": "#eb5760"}, {"source": 19, "target": 25, "value": 1, "colour": "#eb5760"}, {"source": 19, "target": 46, "value": 1, "colour": "#eb5760"}, {"source": 19, "target": 34, "value": 1, "colour": "#eb5760"}, {"source": 19, "target": 28, "value": 1, "colour": "#eb5760"}, {"source": 19, "target": 35, "value": 1, "colour": "#eb5760"}, {"source": 19, "target": 49, "value": 1, "colour": "#eb5760"}, {"source": 19, "target": 50, "value": 1, "colour": "#eb5760"}, {"source": 19, "target": 31, "value": 1, "colour": "#eb5760"}, {"source": 19, "target": 95, "value": 1, "colour": "#eb5760"}, {"source": 19, "target": 32, "value": 1, "colour": "#eb5760"}, {"source": 20, "target": 41, "value": 1, "colour": "#eb5760"}, {"source": 20, "target": 90, "value": 1, "colour": "#eb5760"}, {"source": 20, "target": 71, "value": 1, "colour": "#eb5760"}, {"source": 20, "target": 24, "value": 1, "colour": "#eb5760"}, {"source": 20, "target": 25, "value": 1, "colour": "#eb5760"}, {"source": 20, "target": 83, "value": 1, "colour": "#eb5760"}, {"source": 20, "target": 45, "value": 1, "colour": "#eb5760"}, {"source": 20, "target": 53, "value": 1, "colour": "#eb5760"}, {"source": 20, "target": 93, "value": 1, "colour": "#eb5760"}, {"source": 20, "target": 47, "value": 1, "colour": "#eb5760"}, {"source": 20, "target": 76, "value": 1, "colour": "#eb5760"}, {"source": 20, "target": 99, "value": 1, "colour": "#eb5760"}, {"source": 20, "target": 34, "value": 1, "colour": "#eb5760"}, {"source": 20, "target": 94, "value": 1, "colour": "#eb5760"}, {"source": 20, "target": 27, "value": 1, "colour": "#eb5760"}, {"source": 20, "target": 63, "value": 1, "colour": "#eb5760"}, {"source": 20, "target": 100, "value": 1, "colour": "#eb5760"}, {"source": 20, "target": 64, "value": 1, "colour": "#eb5760"}, {"source": 20, "target": 51, "value": 1, "colour": "#eb5760"}, {"source": 20, "target": 87, "value": 1, "colour": "#eb5760"}, {"source": 20, "target": 101, "value": 1, "colour": "#eb5760"}, {"source": 21, "target": 68, "value": 1, "colour": "#eb5760"}, {"source": 21, "target": 91, "value": 1, "colour": "#eb5760"}, {"source": 21, "target": 23, "value": 1, "colour": "#eb5760"}, {"source": 21, "target": 102, "value": 1, "colour": "#eb5760"}, {"source": 21, "target": 55, "value": 1, "colour": "#eb5760"}, {"source": 21, "target": 56, "value": 1, "colour": "#eb5760"}, {"source": 21, "target": 103, "value": 1, "colour": "#eb5760"}, {"source": 21, "target": 104, "value": 1, "colour": "#eb5760"}, {"source": 21, "target": 46, "value": 1, "colour": "#eb5760"}, {"source": 21, "target": 77, "value": 1, "colour": "#eb5760"}, {"source": 21, "target": 28, "value": 1, "colour": "#eb5760"}, {"source": 21, "target": 105, "value": 1, "colour": "#eb5760"}, {"source": 21, "target": 106, "value": 1, "colour": "#eb5760"}, {"source": 21, "target": 35, "value": 1, "colour": "#eb5760"}, {"source": 21, "target": 48, "value": 1, "colour": "#eb5760"}, {"source": 21, "target": 49, "value": 1, "colour": "#eb5760"}, {"source": 21, "target": 29, "value": 1, "colour": "#eb5760"}, {"source": 21, "target": 64, "value": 1, "colour": "#eb5760"}, {"source": 21, "target": 30, "value": 1, "colour": "#eb5760"}, {"source": 21, "target": 50, "value": 1, "colour": "#eb5760"}, {"source": 21, "target": 107, "value": 1, "colour": "#eb5760"}, {"source": 21, "target": 108, "value": 1, "colour": "#eb5760"}, {"source": 21, "target": 31, "value": 1, "colour": "#eb5760"}, {"source": 21, "target": 32, "value": 1, "colour": "#eb5760"}, {"source": 21, "target": 96, "value": 1, "colour": "#eb5760"}, {"source": 22, "target": 61, "value": 1, "colour": "#eb5760"}, {"source": 22, "target": 62, "value": 1, "colour": "#eb5760"}, {"source": 22, "target": 24, "value": 1, "colour": "#eb5760"}, {"source": 22, "target": 25, "value": 1, "colour": "#eb5760"}, {"source": 22, "target": 46, "value": 1, "colour": "#eb5760"}, {"source": 22, "target": 34, "value": 1, "colour": "#eb5760"}, {"source": 22, "target": 29, "value": 1, "colour": "#eb5760"}, {"source": 23, "target": 109, "value": 1, "colour": "#d3436e"}, {"source": 23, "target": 110, "value": 1, "colour": "#d3436e"}, {"source": 24, "target": 111, "value": 1, "colour": "#d3436e"}, {"source": 26, "target": 112, "value": 1, "colour": "#d3436e"}, {"source": 26, "target": 113, "value": 1, "colour": "#d3436e"}, {"source": 27, "target": 114, "value": 1, "colour": "#d3436e"}, {"source": 27, "target": 115, "value": 1, "colour": "#d3436e"}, {"source": 27, "target": 116, "value": 1, "colour": "#d3436e"}, {"source": 27, "target": 117, "value": 1, "colour": "#d3436e"}, {"source": 27, "target": 118, "value": 1, "colour": "#d3436e"}, {"source": 27, "target": 119, "value": 1, "colour": "#d3436e"}, {"source": 27, "target": 111, "value": 1, "colour": "#d3436e"}, {"source": 27, "target": 120, "value": 1, "colour": "#d3436e"}, {"source": 27, "target": 121, "value": 1, "colour": "#d3436e"}, {"source": 28, "target": 122, "value": 1, "colour": "#d3436e"}, {"source": 28, "target": 123, "value": 1, "colour": "#d3436e"}, {"source": 28, "target": 124, "value": 1, "colour": "#d3436e"}, {"source": 28, "target": 125, "value": 1, "colour": "#d3436e"}, {"source": 29, "target": 118, "value": 1, "colour": "#d3436e"}, {"source": 29, "target": 119, "value": 1, "colour": "#d3436e"}, {"source": 29, "target": 124, "value": 1, "colour": "#d3436e"}, {"source": 29, "target": 125, "value": 1, "colour": "#d3436e"}, {"source": 29, "target": 126, "value": 1, "colour": "#d3436e"}, {"source": 30, "target": 127, "value": 1, "colour": "#d3436e"}, {"source": 30, "target": 128, "value": 1, "colour": "#d3436e"}, {"source": 30, "target": 129, "value": 1, "colour": "#d3436e"}, {"source": 30, "target": 130, "value": 1, "colour": "#d3436e"}, {"source": 31, "target": 124, "value": 1, "colour": "#d3436e"}, {"source": 31, "target": 125, "value": 1, "colour": "#d3436e"}, {"source": 33, "target": 131, "value": 1, "colour": "#d3436e"}, {"source": 33, "target": 132, "value": 1, "colour": "#d3436e"}, {"source": 33, "target": 133, "value": 1, "colour": "#d3436e"}, {"source": 33, "target": 134, "value": 1, "colour": "#d3436e"}, {"source": 35, "target": 135, "value": 1, "colour": "#d3436e"}, {"source": 35, "target": 136, "value": 1, "colour": "#d3436e"}, {"source": 35, "target": 124, "value": 1, "colour": "#d3436e"}, {"source": 35, "target": 125, "value": 1, "colour": "#d3436e"}, {"source": 35, "target": 126, "value": 1, "colour": "#d3436e"}, {"source": 35, "target": 110, "value": 1, "colour": "#d3436e"}, {"source": 38, "target": 110, "value": 1, "colour": "#d3436e"}, {"source": 39, "target": 137, "value": 1, "colour": "#d3436e"}, {"source": 39, "target": 117, "value": 1, "colour": "#d3436e"}, {"source": 39, "target": 138, "value": 1, "colour": "#d3436e"}, {"source": 39, "target": 122, "value": 1, "colour": "#d3436e"}, {"source": 39, "target": 123, "value": 1, "colour": "#d3436e"}, {"source": 39, "target": 124, "value": 1, "colour": "#d3436e"}, {"source": 39, "target": 125, "value": 1, "colour": "#d3436e"}, {"source": 39, "target": 139, "value": 1, "colour": "#d3436e"}, {"source": 42, "target": 114, "value": 1, "colour": "#d3436e"}, {"source": 42, "target": 140, "value": 1, "colour": "#d3436e"}, {"source": 42, "target": 122, "value": 1, "colour": "#d3436e"}, {"source": 42, "target": 123, "value": 1, "colour": "#d3436e"}, {"source": 42, "target": 118, "value": 1, "colour": "#d3436e"}, {"source": 42, "target": 119, "value": 1, "colour": "#d3436e"}, {"source": 42, "target": 124, "value": 1, "colour": "#d3436e"}, {"source": 42, "target": 125, "value": 1, "colour": "#d3436e"}, {"source": 42, "target": 141, "value": 1, "colour": "#d3436e"}, {"source": 42, "target": 121, "value": 1, "colour": "#d3436e"}, {"source": 43, "target": 142, "value": 1, "colour": "#d3436e"}, {"source": 43, "target": 143, "value": 1, "colour": "#d3436e"}, {"source": 45, "target": 144, "value": 1, "colour": "#d3436e"}, {"source": 45, "target": 145, "value": 1, "colour": "#d3436e"}, {"source": 45, "target": 110, "value": 1, "colour": "#d3436e"}, {"source": 46, "target": 124, "value": 1, "colour": "#d3436e"}, {"source": 46, "target": 125, "value": 1, "colour": "#d3436e"}, {"source": 46, "target": 126, "value": 1, "colour": "#d3436e"}, {"source": 48, "target": 141, "value": 1, "colour": "#d3436e"}, {"source": 49, "target": 146, "value": 1, "colour": "#d3436e"}, {"source": 49, "target": 131, "value": 1, "colour": "#d3436e"}, {"source": 49, "target": 132, "value": 1, "colour": "#d3436e"}, {"source": 49, "target": 133, "value": 1, "colour": "#d3436e"}, {"source": 49, "target": 122, "value": 1, "colour": "#d3436e"}, {"source": 49, "target": 123, "value": 1, "colour": "#d3436e"}, {"source": 49, "target": 111, "value": 1, "colour": "#d3436e"}, {"source": 49, "target": 147, "value": 1, "colour": "#d3436e"}, {"source": 49, "target": 148, "value": 1, "colour": "#d3436e"}, {"source": 53, "target": 149, "value": 1, "colour": "#d3436e"}, {"source": 53, "target": 122, "value": 1, "colour": "#d3436e"}, {"source": 53, "target": 123, "value": 1, "colour": "#d3436e"}, {"source": 53, "target": 124, "value": 1, "colour": "#d3436e"}, {"source": 53, "target": 125, "value": 1, "colour": "#d3436e"}, {"source": 53, "target": 150, "value": 1, "colour": "#d3436e"}, {"source": 53, "target": 110, "value": 1, "colour": "#d3436e"}, {"source": 55, "target": 142, "value": 1, "colour": "#d3436e"}, {"source": 55, "target": 118, "value": 1, "colour": "#d3436e"}, {"source": 55, "target": 119, "value": 1, "colour": "#d3436e"}, {"source": 55, "target": 111, "value": 1, "colour": "#d3436e"}, {"source": 55, "target": 141, "value": 1, "colour": "#d3436e"}, {"source": 56, "target": 141, "value": 1, "colour": "#d3436e"}, {"source": 57, "target": 151, "value": 1, "colour": "#d3436e"}, {"source": 57, "target": 152, "value": 1, "colour": "#d3436e"}, {"source": 57, "target": 153, "value": 1, "colour": "#d3436e"}, {"source": 57, "target": 154, "value": 1, "colour": "#d3436e"}, {"source": 57, "target": 155, "value": 1, "colour": "#d3436e"}, {"source": 58, "target": 116, "value": 1, "colour": "#d3436e"}, {"source": 58, "target": 156, "value": 1, "colour": "#d3436e"}, {"source": 59, "target": 135, "value": 1, "colour": "#d3436e"}, {"source": 59, "target": 136, "value": 1, "colour": "#d3436e"}, {"source": 59, "target": 157, "value": 1, "colour": "#d3436e"}, {"source": 59, "target": 158, "value": 1, "colour": "#d3436e"}, {"source": 60, "target": 159, "value": 1, "colour": "#d3436e"}, {"source": 60, "target": 160, "value": 1, "colour": "#d3436e"}, {"source": 62, "target": 124, "value": 1, "colour": "#d3436e"}, {"source": 62, "target": 125, "value": 1, "colour": "#d3436e"}, {"source": 63, "target": 161, "value": 1, "colour": "#d3436e"}, {"source": 63, "target": 162, "value": 1, "colour": "#d3436e"}, {"source": 63, "target": 163, "value": 1, "colour": "#d3436e"}, {"source": 63, "target": 141, "value": 1, "colour": "#d3436e"}, {"source": 65, "target": 115, "value": 1, "colour": "#d3436e"}, {"source": 65, "target": 122, "value": 1, "colour": "#d3436e"}, {"source": 65, "target": 123, "value": 1, "colour": "#d3436e"}, {"source": 65, "target": 118, "value": 1, "colour": "#d3436e"}, {"source": 65, "target": 119, "value": 1, "colour": "#d3436e"}, {"source": 65, "target": 164, "value": 1, "colour": "#d3436e"}, {"source": 65, "target": 111, "value": 1, "colour": "#d3436e"}, {"source": 66, "target": 116, "value": 1, "colour": "#d3436e"}, {"source": 67, "target": 116, "value": 1, "colour": "#d3436e"}, {"source": 67, "target": 165, "value": 1, "colour": "#d3436e"}, {"source": 68, "target": 166, "value": 1, "colour": "#d3436e"}, {"source": 68, "target": 156, "value": 1, "colour": "#d3436e"}, {"source": 70, "target": 159, "value": 1, "colour": "#d3436e"}, {"source": 70, "target": 167, "value": 1, "colour": "#d3436e"}, {"source": 71, "target": 149, "value": 1, "colour": "#d3436e"}, {"source": 71, "target": 118, "value": 1, "colour": "#d3436e"}, {"source": 71, "target": 119, "value": 1, "colour": "#d3436e"}, {"source": 71, "target": 160, "value": 1, "colour": "#d3436e"}, {"source": 73, "target": 168, "value": 1, "colour": "#d3436e"}, {"source": 73, "target": 163, "value": 1, "colour": "#d3436e"}, {"source": 76, "target": 142, "value": 1, "colour": "#d3436e"}, {"source": 76, "target": 156, "value": 1, "colour": "#d3436e"}, {"source": 77, "target": 141, "value": 1, "colour": "#d3436e"}, {"source": 78, "target": 169, "value": 1, "colour": "#d3436e"}, {"source": 78, "target": 149, "value": 1, "colour": "#d3436e"}, {"source": 78, "target": 170, "value": 1, "colour": "#d3436e"}, {"source": 78, "target": 118, "value": 1, "colour": "#d3436e"}, {"source": 78, "target": 119, "value": 1, "colour": "#d3436e"}, {"source": 78, "target": 124, "value": 1, "colour": "#d3436e"}, {"source": 78, "target": 125, "value": 1, "colour": "#d3436e"}, {"source": 78, "target": 139, "value": 1, "colour": "#d3436e"}, {"source": 78, "target": 171, "value": 1, "colour": "#d3436e"}, {"source": 81, "target": 172, "value": 1, "colour": "#d3436e"}, {"source": 81, "target": 127, "value": 1, "colour": "#d3436e"}, {"source": 81, "target": 156, "value": 1, "colour": "#d3436e"}, {"source": 81, "target": 173, "value": 1, "colour": "#d3436e"}, {"source": 81, "target": 174, "value": 1, "colour": "#d3436e"}, {"source": 81, "target": 111, "value": 1, "colour": "#d3436e"}, {"source": 81, "target": 160, "value": 1, "colour": "#d3436e"}, {"source": 81, "target": 129, "value": 1, "colour": "#d3436e"}, {"source": 82, "target": 175, "value": 1, "colour": "#d3436e"}, {"source": 83, "target": 175, "value": 1, "colour": "#d3436e"}, {"source": 84, "target": 116, "value": 1, "colour": "#d3436e"}, {"source": 86, "target": 168, "value": 1, "colour": "#d3436e"}, {"source": 86, "target": 116, "value": 1, "colour": "#d3436e"}, {"source": 86, "target": 111, "value": 1, "colour": "#d3436e"}, {"source": 86, "target": 175, "value": 1, "colour": "#d3436e"}, {"source": 87, "target": 172, "value": 1, "colour": "#d3436e"}, {"source": 87, "target": 142, "value": 1, "colour": "#d3436e"}, {"source": 87, "target": 160, "value": 1, "colour": "#d3436e"}, {"source": 89, "target": 156, "value": 1, "colour": "#d3436e"}, {"source": 90, "target": 117, "value": 1, "colour": "#d3436e"}, {"source": 90, "target": 141, "value": 1, "colour": "#d3436e"}, {"source": 91, "target": 124, "value": 1, "colour": "#d3436e"}, {"source": 91, "target": 125, "value": 1, "colour": "#d3436e"}, {"source": 93, "target": 115, "value": 1, "colour": "#d3436e"}, {"source": 93, "target": 117, "value": 1, "colour": "#d3436e"}, {"source": 93, "target": 156, "value": 1, "colour": "#d3436e"}, {"source": 93, "target": 124, "value": 1, "colour": "#d3436e"}, {"source": 93, "target": 125, "value": 1, "colour": "#d3436e"}, {"source": 93, "target": 111, "value": 1, "colour": "#d3436e"}, {"source": 93, "target": 176, "value": 1, "colour": "#d3436e"}, {"source": 93, "target": 177, "value": 1, "colour": "#d3436e"}, {"source": 93, "target": 141, "value": 1, "colour": "#d3436e"}, {"source": 93, "target": 121, "value": 1, "colour": "#d3436e"}, {"source": 95, "target": 162, "value": 1, "colour": "#d3436e"}, {"source": 95, "target": 178, "value": 1, "colour": "#d3436e"}, {"source": 95, "target": 179, "value": 1, "colour": "#d3436e"}, {"source": 95, "target": 180, "value": 1, "colour": "#d3436e"}, {"source": 96, "target": 179, "value": 1, "colour": "#d3436e"}, {"source": 96, "target": 140, "value": 1, "colour": "#d3436e"}, {"source": 96, "target": 181, "value": 1, "colour": "#d3436e"}, {"source": 97, "target": 171, "value": 1, "colour": "#d3436e"}, {"source": 98, "target": 182, "value": 1, "colour": "#d3436e"}, {"source": 98, "target": 138, "value": 1, "colour": "#d3436e"}, {"source": 98, "target": 183, "value": 1, "colour": "#d3436e"}, {"source": 98, "target": 184, "value": 1, "colour": "#d3436e"}, {"source": 98, "target": 160, "value": 1, "colour": "#d3436e"}, {"source": 99, "target": 159, "value": 1, "colour": "#d3436e"}, {"source": 100, "target": 141, "value": 1, "colour": "#d3436e"}, {"source": 101, "target": 117, "value": 1, "colour": "#d3436e"}, {"source": 101, "target": 185, "value": 1, "colour": "#d3436e"}, {"source": 101, "target": 141, "value": 1, "colour": "#d3436e"}, {"source": 101, "target": 121, "value": 1, "colour": "#d3436e"}, {"source": 102, "target": 116, "value": 1, "colour": "#d3436e"}, {"source": 106, "target": 186, "value": 1, "colour": "#d3436e"}, {"source": 107, "target": 111, "value": 1, "colour": "#d3436e"}, {"source": 110, "target": 187, "value": 1, "colour": "#b5367a"}, {"source": 112, "target": 188, "value": 1, "colour": "#b5367a"}, {"source": 112, "target": 189, "value": 1, "colour": "#b5367a"}, {"source": 116, "target": 187, "value": 1, "colour": "#b5367a"}, {"source": 116, "target": 190, "value": 1, "colour": "#b5367a"}, {"source": 118, "target": 187, "value": 1, "colour": "#b5367a"}, {"source": 118, "target": 191, "value": 1, "colour": "#b5367a"}, {"source": 121, "target": 192, "value": 1, "colour": "#b5367a"}, {"source": 125, "target": 193, "value": 1, "colour": "#b5367a"}, {"source": 133, "target": 194, "value": 1, "colour": "#b5367a"}, {"source": 133, "target": 195, "value": 1, "colour": "#b5367a"}, {"source": 138, "target": 196, "value": 1, "colour": "#b5367a"}, {"source": 138, "target": 197, "value": 1, "colour": "#b5367a"}, {"source": 138, "target": 198, "value": 1, "colour": "#b5367a"}, {"source": 150, "target": 199, "value": 1, "colour": "#b5367a"}, {"source": 150, "target": 196, "value": 1, "colour": "#b5367a"}, {"source": 152, "target": 200, "value": 1, "colour": "#b5367a"}, {"source": 155, "target": 201, "value": 1, "colour": "#b5367a"}, {"source": 156, "target": 195, "value": 1, "colour": "#b5367a"}, {"source": 156, "target": 202, "value": 1, "colour": "#b5367a"}, {"source": 157, "target": 203, "value": 1, "colour": "#b5367a"}, {"source": 157, "target": 204, "value": 1, "colour": "#b5367a"}, {"source": 161, "target": 205, "value": 1, "colour": "#b5367a"}, {"source": 169, "target": 206, "value": 1, "colour": "#b5367a"}, {"source": 170, "target": 207, "value": 1, "colour": "#b5367a"}, {"source": 170, "target": 208, "value": 1, "colour": "#b5367a"}, {"source": 170, "target": 209, "value": 1, "colour": "#b5367a"}, {"source": 170, "target": 210, "value": 1, "colour": "#b5367a"}, {"source": 170, "target": 211, "value": 1, "colour": "#b5367a"}, {"source": 176, "target": 212, "value": 1, "colour": "#b5367a"}, {"source": 177, "target": 192, "value": 1, "colour": "#b5367a"}, {"source": 178, "target": 213, "value": 1, "colour": "#b5367a"}, {"source": 200, "target": 214, "value": 1, "colour": "#982d80"}, {"source": 203, "target": 215, "value": 1, "colour": "#982d80"}, {"source": 209, "target": 216, "value": 1, "colour": "#982d80"}, {"source": 215, "target": 217, "value": 1, "colour": "#7b2382"}, {"source": 215, "target": 218, "value": 1, "colour": "#7b2382"}]}